seedphotos/__init__.py
seedphotos/photos.py
seedphotos-0.1.3.dist-info/LICENSE
seedphotos-0.1.3.dist-info/WHEEL
seedphotos-0.1.3.dist-info/METADATA
seedphotos-0.1.3.dist-info/RECORD
