Metadata-Version: 2.1
Name: seedphotos
Version: 0.1.3
Summary: A lib that create image through words
License: MIT
Author: Vinicius Barbosa de Aguiar
Author-email: vb9763662@gmail.com
Requires-Python: >=3.8,<4.0
Classifier: License :: OSI Approved :: MIT License
Classifier: Programming Language :: Python :: 3
Classifier: Programming Language :: Python :: 3.10
Classifier: Programming Language :: Python :: 3.8
Classifier: Programming Language :: Python :: 3.9
Requires-Dist: requests (>=2.27.1,<3.0.0)
